Mymacroprocessor/Mymacroprocessor.py
Mymacroprocessor/__init__.py
Mymacroprocessor/_init_.py
Mymacroprocessor-0.0.3.dist-info/LICENSE
Mymacroprocessor-0.0.3.dist-info/METADATA
Mymacroprocessor-0.0.3.dist-info/WHEEL
Mymacroprocessor-0.0.3.dist-info/top_level.txt
Mymacroprocessor-0.0.3.dist-info/RECORD
