Metadata-Version: 2.1
Name: Mymacroprocessor
Version: 0.0.3
Summary: python file macro processor
Home-page: https://github.com/nufeng1999/Mymacroprocessor/
Author: nufeng
Author-email: 18478162@qq.com
License: apache 3.0
Download-URL: https://github.com/nufeng1999/Mymacroprocessor/releases/tag/0.0.3
Keywords: python,macro,processor,if,ifdef,ifndef,elif,else,endif,defined,define,undef
Platform: UNKNOWN
Classifier: Programming Language :: Python :: 3
Classifier: License :: OSI Approved :: MIT License
Classifier: Operating System :: OS Independent
Requires: re
License-File: LICENSE
